Metadata-Version: 2.1
Name: rhasspy-rasa-nlu-hermes
Version: 0.4.1
Summary: UNKNOWN
Home-page: https://github.com/rhasspy/rhasspy-rasa-nlu-hermes
Author: Michael Hansen
Author-email: mike@rhasspy.org
License: UNKNOWN
Platform: UNKNOWN
Classifier: Programming Language :: Python :: 3
Classifier: License :: OSI Approved :: MIT License
Requires-Python: >=3.7
